{
  "ogmoVersion": "3.4.0",
  "width": 1600,
  "height": 864,
  "offsetX": 0,
  "offsetY": 0,
  "layers": [
    {
      "name": "entities",
      "_eid": "72465116",
      "offsetX": 0,
      "offsetY": 0,
      "gridCellWidth": 16,
      "gridCellHeight": 16,
      "gridCellsX": 100,
      "gridCellsY": 54,
      "entities": [
        {"name": "prey", "id": 0, "_eid": "72472484", "x": 192, "y": 416, "originX": 0, "originY": 0},
        {"name": "prey", "id": 1, "_eid": "72472484", "x": 1072, "y": 592, "originX": 0, "originY": 0},
        {"name": "predator", "id": 2, "_eid": "72474834", "x": 976, "y": 112, "originX": 0, "originY": 0},
        {"name": "prey", "id": 3, "_eid": "72472484", "x": 176, "y": 336, "originX": 0, "originY": 0},
        {"name": "prey", "id": 4, "_eid": "72472484", "x": 944, "y": 272, "originX": 0, "originY": 0},
        {"name": "prey", "id": 5, "_eid": "72472484", "x": 1360, "y": 432, "originX": 0, "originY": 0},
        {"name": "prey", "id": 6, "_eid": "72472484", "x": 432, "y": 224, "originX": 0, "originY": 0},
        {"name": "prey", "id": 7, "_eid": "72472484", "x": 528, "y": 448, "originX": 0, "originY": 0},
        {"name": "prey", "id": 8, "_eid": "72472484", "x": 464, "y": 528, "originX": 0, "originY": 0},
        {"name": "prey", "id": 9, "_eid": "72472484", "x": 1088, "y": 544, "originX": 0, "originY": 0},
        {"name": "prey", "id": 10, "_eid": "72472484", "x": 1280, "y": 544, "originX": 0, "originY": 0},
        {"name": "prey", "id": 11, "_eid": "72472484", "x": 352, "y": 544, "originX": 0, "originY": 0},
        {"name": "prey", "id": 12, "_eid": "72472484", "x": 464, "y": 256, "originX": 0, "originY": 0},
        {"name": "prey", "id": 13, "_eid": "72472484", "x": 1424, "y": 448, "originX": 0, "originY": 0},
        {"name": "predator", "id": 14, "_eid": "72474834", "x": 752, "y": 752, "originX": 0, "originY": 0},
        {"name": "cave", "id": 15, "_eid": "72487415", "x": 816, "y": 400, "originX": 0, "originY": 0},
        {"name": "player", "id": 16, "_eid": "72460224", "x": 800, "y": 400, "originX": 0, "originY": 0}
      ]
    },
    {
      "name": "obstacles",
      "_eid": "72467368",
      "offsetX": 0,
      "offsetY": 0,
      "gridCellWidth": 16,
      "gridCellHeight": 16,
      "gridCellsX": 100,
      "gridCellsY": 54,
      "tileset": "tiles",
      "data": [16, 16, 16, 16, 16, 16, 16, 16, 16, 16, 16, 16, 16, 16, 16, 16, 16, 16, 16, 16, 16, 16, 16, 16, 16, 16, 16, 16, 16, 16, 16, 16, 16, 16, 16, 16, 16, 16, 16, 16, 16, 16, 16, 16, 16, 16, 16, 16, 16, 16, 16, 16, 16, 16, 16, 16, 16, 16, 16, 16, 16, 16, 16, 16, 16, 16, 16, 16, 16, 16, 16, 16, 16, 16, 16, 16, 16, 16, 16, 16, 16, 16, 16, 16, 16, 16, 16, 16, 16, 16, 16, 16, 16, 16, 16, 16, 16, 16, 16, 16, 16, 16, 16, 16, 16, 16, 16, 16, 16, 16, 16, 16, 16, 16, 16, 16, 16, 16, 16, 16, 16, 16, 16, 16, 16, 16, 16, 16, 16, 16, 16, 16, 16, 16, 16, 16, 16, 16, 16, 16, 16, 16, 16, 16, 16, 16, 16, 16, 16, 16, 16, 16, 16, 16, 16, 16, 16, 16, 16, 16, 16, 16, 16, 16, 16, 16, 16, 16, 16, 16, 16, 16, 16, 16, 16, 16, 16, 16, 16, 16, 16, 16, 16, 16, 16, 16, 16, 16, 16, 16, 16, 16, 16, 16, 16, 16, 16, 16, 16, 16, 16, 16, 16, 16, 16, 16, 16, 16, 16, 16, 16, 16, 16, 16, 16, 16, 16, 16, 16, 16, 16, 16, 16, 16, 16, 16, 16, 16, 16, 16, 16, 16, 16, 16, 16, 16, 16, 16, 16, 16, 16, 16, 16, 16, 16, 16, 16, 16, 16, 16, 16, 49, 50, 50, 50, 50, 50, 50, 50, 50, 50, 50, 51, 16, 16, 16, 16, 16, 16, 16, 16, 16, 16, 16, 16, 16, 16, 16, 16, 16, 16, 16, 16, 16, 16, 16, 16, 16, 16, 16, 16, 16, 16, 16, 16, 16, 16, 16, 16, 16, 16, 16, 16, 16, 16, 16, 16, 16, 16, 16, 16, 16, 16, 16, 16, 16, 16, 16, 16, 16, 16, 16, 16, 16, 16, 16, 16, 16, 16, 16, 16, 16, 16, 16, 16, 16, 16, 16, 16, 16, 16, 16, 16, 16, 16, 16, 16, 16, 16, 49, 50, 59, -1, -1, -1, -1, -1, -1, -1, -1, -1, -1, 60, 50, 50, 51, 16, 16, 16, 16, 16, 16, 16, 16, 16, 16, 16, 16, 16, 16, 16, 16, 16, 16, 16, 16, 16, 16, 16, 16, 16, 16, 16, 16, 16, 16, 16, 16, 16, 16, 16, 16, 16, 16, 16, 16, 16, 16, 16, 16, 16, 16, 16, 16, 16, 16, 16, 16, 16, 16, 16, 16, 16, 16, 16, 16, 16, 16, 16, 16, 16, 16, 16, 16, 16, 16, 16, 16, 16, 16, 16, 16, 16, 16, 16, 16, 16, 16, 16, 56, -1, -1, -1, -1, -1, -1, -1, -1, -1, -1, -1, -1, -1, -1, -1, 60, 50, 51, 16, 16, 16, 16, 16, 16, 16, 16, 16, 16, 16, 16, 16, 16, 16, 16, 16, 16, 16, 16, 16, 16, 16, 16, 16, 16, 16, 16, 16, 16, 16, 16, 16, 16, 16, 16, 16, 16, 16, 16, 16, 16, 16, 16, 16, 16, 16, 16, 16, 16, 16, 16, 16, 16, 16, 16, 16, 16, 16, 16, 16, 16, 16, 49, 50, 51, 16, 16, 16, 16, 16, 16, 16, 16, 16, 16, 16, 16, 16, 16, 16, 56, -1, -1, -1, -1, -1, -1, -1, -1, -1, -1, -1, -1, -1, -1, -1, -1, -1, 60, 50, 51, 16, 16, 49, 50, 50, 50, 50, 51, 16, 16, 16, 16, 16, 16, 16, 16, 16, 16, 16, 16, 16, 16, 16, 16, 16, 16, 16, 16, 16, 16, 16, 16, 16, 16, 16, 16, 16, 16, 16, 16, 16, 16, 16, 16, 16, 16, 16, 16, 16, 16, 16, 16, 16, 16, 16, 16, 16, 49, 50, 50, 50, 59, -1, 60, 51, 16, 16, 16, 16, 16, 16, 16, 16, 16, 16, 16, 16, 16, 16, 63, 64, 66, -1, -1, -1, -1, -1, -1, -1, -1, -1, -1, -1, -1, -1, -1, -1, -1, -1, 60, 50, 50, 59, -1, -1, -1, -1, 58, 16, 16, 16, 16, 16, 16, 16, 16, 16, 16, 16, 16, 16, 16, 16, 16, 16, 16, 16, 16, 16, 16, 16, 16, 16, 16, 16, 16, 16, 16, 16, 16, 16, 16, 16, 16, 16, 16, 16, 16, 16, 16, 16, 16, 16, 16, 16, 49, 50, 59, -1, 21, -1, -1, -1, 22, 60, 51, 16, 16, 16, 16, 16, 16, 16, 16, 16, 16, 16, 16, 16, 16, 16, 63, 66, -1, 22, -1, -1, -1, -1, -1, -1, -1, -1, -1, -1, -1, 21, -1, -1, -1, 21, -1, -1, -1, -1, -1, -1, 58, 16, 16, 16, 16, 16, 16, 16, 16, 16, 16, 16, 16, 16, 16, 16, 16, 16, 16, 16, 16, 16, 16, 16, 16, 16, 16, 16, 16, 16, 16, 16, 16, 16, 16, 16, 16, 16, 16, 16, 16, 16, 16, 16, 16, 16, 16, 16, 56, -1, 21, -1, -1, -1, -1, -1, -1, 21, 58, 16, 16, 16, 16, 16, 16, 16, 16, 16, 16, 16, 16, 16, 16, 16, 16, 56, -1, -1, -1, -1, -1, 15, -1, -1, -1, -1, -1, -1, 21, -1, -1, -1, -1, -1, -1, -1, -1, -1, -1, 67, 65, 16, 16, 16, 16, 16, 16, 16, 16, 16, 16, 16, 16, 16, 16, 16, 16, 16, 16, 16, 16, 16, 16, 16, 16, 16, 16, 16, 16, 16, 16, 16, 16, 16, 16, 16, 16, 16, 16, 16, 16, 16, 16, 16, 16, 16, 49, 50, 59, -1, -1, -1, -1, -1, -1, -1, -1, -1, 58, 16, 16, 16, 16, 16, 16, 16, 16, 16, 16, 16, 16, 16, 16, 16, 49, 59, 22, -1, -1, -1, -1, -1, -1, -1, -1, -1, -1, -1, -1, -1, -1, -1, -1, -1, -1, -1, -1, -1, -1, 58, 16, 16, 16, 16, 16, 16, 16, 16, 16, 16, 16, 16, 16, 16, 16, 16, 16, 16, 16, 16, 16, 16, 16, 16, 16, 16, 16, 16, 16, 16, 16, 16, 16, 16, 16, 16, 16, 16, 16, 16, 16, 16, 16, 49, 50, 50, 59, -1, -1, -1, -1, -1, 28, 29, 29, 30, -1, -1, 58, 16, 16, 16, 16, 16, 16, 16, 16, 16, 16, 16, 16, 16, 16, 16, 56, -1, -1, -1, -1, -1, -1, 28, -1, -1, -1, -1, -1, -1, -1, -1, -1, -1, -1, -1, -1, -1, -1, -1, 67, 65, 16, 16, 16, 16, 16, 16, 16, 16, 16, 16, 16, 16, 16, 16, 16, 16, 16, 16, 16, 16, 16, 16, 16, 16, 16, 16, 16, 16, 16, 16, 16, 16, 16, 16, 16, 16, 16, 16, 16, 16, 49, 50, 50, 59, -1, -1, -1, -1, -1, 22, 28, 29, 31, -1, 39, 44, -1, -1, 58, 16, 16, 16, 16, 16, 16, 16, 16, 16, 16, 16, 16, 16, 16, 16, 56, -1, -1, -1, -1, 28, 29, 31, -1, -1, -1, -1, -1, 30, -1, -1, -1, -1, -1, -1, -1, -1, -1, -1, 58, 16, 16, 16, 16, 16, 16, 16, 16, 16, 16, 16, 16, 16, 16, 16, 16, 16, 16, 16, 16, 16, 16, 16, 16, 16, 16, 16, 16, 16, 16, 16, 16, 16, 16, 16, 16, 16, 16, 16, 16, 49, 59, -1, -1, -1, -1, -1, -1, -1, 28, 29, 31, -1, -1, 39, 44, -1, -1, -1, 58, 16, 16, 16, 16, 16, 16, 16, 16, 16, 16, 16, 16, 16, 16, 49, 59, -1, -1, -1, -1, 35, -1, -1, -1, -1, -1, -1, -1, 32, 29, 30, -1, -1, -1, -1, -1, -1, -1, -1, 60, 50, 50, 50, 50, 50, 50, 50, 50, 51, 16, 16, 16, 16, 16, 16, 16, 16, 16, 16, 16, 16, 16, 16, 16, 16, 16, 16, 16, 16, 16, 16, 16, 16, 16, 16, 16, 16, 16, 16, 49, 59, -1, -1, -1, 21, -1, -1, -1, 28, 31, -1, -1, -1, 14, 37, -1, -1, -1, 67, 65, 16, 16, 16, 16, 16, 16, 16, 16, 16, 16, 16, 16, 16, 16, 56, -1, -1, -1, -1, -1, 35, -1, -1, -1, -1, -1, -1, -1, -1, -1, 32, 30, -1, -1, -1, -1, -1, -1, -1, -1, -1, -1, -1, -1, -1, -1, -1, -1, 58, 16, 16, 16, 16, 16, 16, 16, 16, 16, 16, 16, 16, 16, 16, 16, 16, 16, 16, 16, 16, 16, 16, 16, 16, 16, 16, 16, 16, 16, 16, 56, -1, -1, -1, -1, -1, -1, -1, 28, 31, -1, -1, -1, -1, -1, 37, -1, -1, 67, 65, 16, 16, 16, 16, 16, 16, 16, 16, 16, 16, 16, 16, 16, 49, 50, 59, -1, 21, -1, -1, 28, 31, -1, -1, -1, -1, -1, -1, -1, -1, -1, -1, 32, 30, -1, -1, -1, -1, -1, -1, -1, -1, 21, -1, -1, -1, -1, -1, -1, 58, 16, 16, 16, 16, 16, 16, 16, 16, 16, 16, 16, 16, 16, 16, 16, 16, 16, 16, 16, 16, 49, 50, 50, 50, 51, 16, 16, 16, 16, 16, 63, 66, -1, -1, -1, -1, -1, -1, 42, 38, -1, -1, -1, -1, -1, -1, -1, -1, 58, 16, 16, 16, 16, 16, 16, 16, 16, 16, 16, 16, 16, 16, 49, 59, -1, -1, -1, -1, -1, 28, 31, -1, -1, -1, -1, -1, -1, -1, -1, -1, -1, -1, -1, 32, 29, 29, 30, -1, -1, -1, -1, -1, -1, 15, -1, -1, -1, -1, -1, 58, 16, 16, 16, 16, 16, 16, 16, 16, 16, 16, 16, 16, 16, 16, 16, 16, 16, 16, 16, 16, 56, -1, -1, 22, 60, 51, 16, 16, 16, 16, 16, 63, 64, 64, 64, 66, -1, -1, -1, 42, 43, 43, -1, -1, -1, -1, -1, -1, 58, 16, 16, 16, 16, 16, 16, 16, 16, 16, 16, 16, 16, 49, 59, -1, -1, 14, -1, -1, 28, 31, -1, -1, 28, 31, -1, -1, -1, -1, 21, -1, -1, 22, -1, -1, -1, -1, 32, 29, 30, -1, -1, -1, -1, -1, -1, -1, -1, -1, 21, 58, 16, 16, 16, 16, 16, 16, 16, 16, 16, 16, 16, 16, 16, 16, 16, 16, 16, 16, 16, 49, 59, -1, -1, -1, -1, 60, 51, 16, 16, 16, 16, 16, 16, 16, 16, 63, 66, -1, -1, -1, -1, -1, -1, -1, -1, -1, -1, -1, 60, 51, 16, 16, 16, 16, 16, 16, 16, 16, 16, 16, 49, 59, -1, -1, -1, -1, -1, 28, 31, -1, -1, 28, 31, -1, -1, -1, -1, -1, 30, -1, -1, 22, -1, -1, -1, -1, -1, 15, 37, -1, 14, -1, -1, -1, -1, -1, -1, -1, -1, 58, 16, 16, 16, 16, 16, 16, 16, 16, 16, 16, 16, 16, 16, 16, 16, 16, 16, 16, 49, 59, -1, -1, -1, -1, -1, -1, 60, 51, 16, 16, 16, 16, 16, 16, 16, 16, 56, -1, -1, -1, -1, -1, -1, -1, 21, -1, -1, -1, -1, 60, 51, 16, 16, 16, 16, 16, 16, 16, 49, 50, 59, -1, -1, -1, -1, -1, 28, 31, -1, -1, -1, 35, 21, -1, -1, -1, -1, -1, 32, 29, 30, -1, -1, -1, -1, -1, 21, -1, 37, -1, -1, -1, -1, -1, -1, -1, -1, -1, -1, 58, 16, 16, 16, 16, 16, 16, 16, 16, 16, 16, 16, 16, 16, 16, 16, 16, 16, 16, 56, -1, -1, -1, -1, -1, -1, -1, -1, 60, 51, 16, 16, 16, 16, 16, 16, 16, 63, 64, 64, 66, -1, -1, -1, -1, 21, -1, -1, -1, -1, -1, 60, 50, 51, 16, 16, 49, 50, 50, 59, -1, -1, -1, -1, -1, -1, 29, 31, -1, -1, -1, 28, 31, -1, -1, -1, -1, -1, -1, -1, 39, 44, -1, -1, -1, -1, -1, -1, 39, 44, -1, -1, -1, -1, -1, -1, -1, -1, -1, 67, 65, 16, 16, 16, 16, 16, 16, 16, 16, 16, 16, 16, 16, 16, 16, 16, 16, 16, 16, 56, -1, -1, -1, -1, -1, -1, -1, -1, -1, 58, 16, 16, 16, 16, 16, 16, 16, 16, 16, 16, 63, 64, 64, 64, 66, -1, -1, -1, -1, -1, -1, -1, 21, 60, 50, 50, 59, -1, 21, -1, -1, -1, -1, -1, -1, -1, -1, -1, -1, -1, 28, 31, -1, -1, -1, -1, -1, 39, 43, 43, 44, -1, -1, -1, -1, -1, 22, 39, 44, 22, -1, -1, -1, -1, -1, -1, -1, -1, 67, 65, 16, 16, 16, 16, 16, 16, 16, 16, 16, 16, 16, 16, 16, 16, 16, 16, 16, 16, 16, 63, 66, -1, -1, 15, -1, -1, -1, -1, -1, 60, 51, 16, 16, 16, 16, 16, 16, 16, 16, 16, 16, 16, 16, 16, 63, 66, -1, -1, -1, 15, -1, -1, -1, -1, -1, -1, -1, -1, -1, -1, -1, -1, -1, -1, -1, -1, -1, -1, -1, -1, -1, -1, -1, -1, -1, 39, 43, 44, -1, -1, -1, -1, -1, -1, -1, -1, 39, 44, -1, -1, -1, -1, -1, -1, -1, -1, -1, -1, 58, 16, 16, 16, 16, 16, 16, 16, 16, 16, 16, 16, 16, 16, 16, 16, 16, 16, 16, 16, 16, 16, 63, 66, -1, -1, -1, -1, -1, -1, -1, -1, 60, 51, 16, 16, 16, 16, 16, 16, 16, 16, 16, 16, 16, 16, 16, 56, -1, -1, -1, -1, -1, -1, -1, -1, -1, -1, -1, -1, -1, -1, -1, -1, -1, -1, -1, -1, -1, -1, -1, -1, -1, -1, -1, -1, -1, 37, 21, -1, -1, -1, -1, -1, 39, 43, 43, 43, 44, -1, -1, -1, -1, -1, -1, -1, -1, -1, -1, -1, 60, 50, 50, 50, 50, 50, 50, 50, 50, 50, 51, 16, 16, 16, 16, 16, 16, 16, 16, 16, 16, 16, 16, 63, 66, -1, -1, -1, -1, -1, 22, -1, -1, 60, 51, 16, 16, 16, 16, 16, 16, 16, 16, 16, 16, 16, 16, 56, -1, -1, -1, -1, -1, 28, 29, 29, -1, -1, -1, -1, -1, -1, -1, -1, -1, -1, -1, -1, -1, -1, -1, -1, -1, -1, -1, -1, 39, 44, -1, -1, -1, -1, 39, 43, 44, -1, -1, -1, -1, -1, -1, -1, -1, -1, -1, -1, -1, -1, -1, -1, -1, -1, -1, -1, -1, -1, -1, -1, -1, -1, 60, 50, 51, 16, 16, 16, 16, 16, 16, 16, 16, 16, 16, 16, 63, 64, 66, -1, -1, -1, -1, -1, -1, -1, 58, 16, 16, 16, 16, 16, 16, 16, 16, 16, 16, 49, 50, 59, -1, -1, -1, -1, 28, 31, 21, -1, -1, -1, -1, -1, -1, -1, -1, -1, -1, -1, -1, -1, -1, 40, -1, -1, -1, -1, -1, -1, 44, 22, -1, -1, -1, -1, 37, -1, -1, -1, -1, -1, -1, -1, 67, 64, 64, 66, -1, -1, 21, -1, -1, -1, -1, -1, -1, -1, -1, -1, -1, 53, -1, -1, 22, -1, 58, 16, 16, 16, 16, 16, 16, 16, 16, 16, 16, 16, 16, 16, 63, 66, -1, -1, -1, -1, -1, 21, 60, 51, 16, 16, 16, 16, 16, 49, 50, 50, 50, 59, -1, -1, -1, -1, -1, 28, 31, -1, -1, -1, -1, -1, 15, -1, -1, -1, -1, -1, -1, -1, -1, -1, -1, -1, -1, -1, -1, -1, -1, -1, -1, -1, -1, -1, 21, 39, 44, -1, -1, -1, -1, 67, 64, 64, 65, 16, 16, 63, 66, -1, -1, -1, -1, 15, -1, -1, -1, -1, 15, -1, -1, -1, -1, -1, -1, 21, 58, 16, 16, 16, 16, 16, 16, 16, 16, 16, 16, 16, 16, 16, 16, 63, 66, -1, -1, -1, -1, -1, 14, 60, 50, 50, 50, 50, 50, 59, -1, -1, -1, -1, 15, -1, -1, -1, 28, 31, -1, -1, -1, 28, 29, 29, 29, 30, -1, 21, -1, -1, -1, -1, -1, -1, -1, -1, -1, -1, -1, -1, -1, -1, -1, -1, -1, -1, -1, -1, -1, -1, -1, -1, 67, 65, 16, 16, 16, 16, 16, 16, 63, 66, -1, -1, -1, -1, -1, -1, -1, -1, -1, -1, -1, -1, -1, 21, -1, -1, 60, 51, 16, 16, 16, 16, 16, 16, 16, 16, 16, 16, 16, 16, 16, 16, 56, -1, -1, -1, -1, -1, -1, -1, -1, -1, -1, -1, -1, -1, -1, -1, -1, -1, -1, -1, 28, 29, 31, -1, -1, 21, -1, 35, -1, -1, -1, 37, -1, -1, -1, -1, -1, -1, -1, -1, -1, -1, -1, -1, -1, -1, -1, -1, -1, -1, -1, -1, -1, -1, -1, -1, -1, 67, 65, 16, 16, 16, 16, 16, 16, 16, 16, 56, -1, -1, -1, -1, -1, 21, -1, -1, -1, -1, -1, -1, -1, -1, -1, -1, -1, 58, 16, 16, 16, 16, 16, 16, 16, 16, 16, 16, 16, 16, 16, 16, 56, -1, -1, -1, -1, -1, -1, -1, -1, -1, -1, -1, -1, -1, -1, -1, -1, -1, -1, -1, 35, -1, -1, -1, -1, 28, 29, 31, -1, -1, 39, 44, -1, -1, -1, -1, -1, -1, -1, -1, -1, -1, -1, -1, -1, -1, -1, -1, -1, -1, -1, -1, -1, -1, -1, -1, -1, 58, 16, 16, 16, 16, 16, 16, 16, 16, 49, 59, -1, -1, -1, -1, 28, 30, -1, -1, -1, -1, -1, -1, -1, -1, -1, -1, -1, 58, 16, 16, 16, 16, 16, 16, 16, 16, 16, 16, 16, 16, 16, 16, 63, 66, -1, -1, -1, -1, -1, -1, -1, -1, -1, -1, -1, -1, 14, 21, -1, -1, -1, 28, 31, -1, -1, -1, 28, 31, -1, -1, -1, -1, 44, -1, -1, -1, -1, -1, 39, 43, 43, -1, -1, -1, -1, -1, -1, -1, -1, -1, -1, -1, -1, -1, 21, -1, -1, -1, -1, 60, 50, 50, 51, 16, 16, 16, 16, 49, 59, 14, -1, -1, 28, 29, 31, 32, 29, 29, 29, 30, -1, -1, -1, -1, -1, -1, 67, 65, 16, 16, 16, 16, 16, 16, 16, 16, 16, 16, 16, 16, 16, 16, 16, 63, 66, -1, -1, 15, -1, -1, -1, -1, -1, -1, -1, -1, 28, 29, 29, 29, 29, 31, -1, -1, -1, 28, 31, -1, -1, -1, -1, -1, -1, -1, -1, -1, 39, 43, 44, -1, -1, -1, -1, -1, -1, -1, -1, -1, -1, -1, -1, -1, -1, -1, -1, -1, -1, -1, -1, -1, -1, 22, 60, 50, 50, 50, 50, 59, -1, -1, -1, -1, -1, 22, -1, -1, -1, -1, 39, 44, -1, -1, -1, -1, -1, -1, 58, 16, 16, 16, 16, 16, 16, 16, 16, 16, 16, 16, 16, 16, 16, 16, 16, 16, 63, 66, -1, -1, -1, -1, -1, -1, -1, -1, -1, -1, 35, -1, -1, -1, -1, -1, -1, -1, 28, 31, -1, -1, -1, -1, -1, -1, -1, -1, 39, 43, 44, -1, -1, -1, -1, -1, -1, -1, -1, -1, -1, -1, -1, 14, -1, -1, -1, -1, -1, -1, -1, -1, -1, -1, -1, -1, -1, -1, -1, -1, -1, -1, -1, -1, -1, -1, -1, -1, -1, -1, 39, 43, 44, -1, -1, -1, -1, -1, -1, -1, 58, 16, 16, 16, 16, 16, 16, 16, 16, 16, 16, 16, 16, 16, 16, 16, 16, 16, 16, 63, 64, 64, 66, -1, -1, 53, -1, -1, -1, -1, -1, -1, -1, -1, -1, 22, -1, 28, 31, -1, -1, -1, -1, -1, -1, -1, 39, 43, 44, -1, -1, -1, -1, -1, 21, -1, -1, -1, -1, -1, -1, -1, -1, -1, -1, -1, -1, -1, -1, -1, -1, 28, 29, 30, -1, -1, -1, -1, -1, -1, -1, -1, -1, -1, -1, -1, -1, -1, -1, -1, 44, -1, -1, -1, -1, -1, -1, -1, 21, 67, 65, 16, 16, 16, 16, 16, 16, 16, 16, 16, 16, 16, 16, 16, 16, 16, 16, 16, 16, 16, 16, 16, 63, 64, 66, -1, -1, -1, -1, -1, -1, -1, -1, -1, -1, 21, -1, 42, 43, -1, -1, -1, -1, -1, -1, 39, 44, -1, -1, -1, -1, -1, -1, -1, 15, -1, -1, -1, -1, -1, -1, -1, -1, -1, -1, -1, 28, 29, 29, 29, 29, 31, -1, 32, 29, 29, 29, -1, -1, -1, -1, -1, -1, -1, -1, -1, -1, -1, -1, -1, -1, 15, -1, -1, -1, -1, -1, -1, -1, 58, 16, 16, 16, 16, 16, 16, 16, 16, 16, 16, 16, 16, 16, 16, 16, 16, 16, 16, 16, 16, 16, 16, 16, 16, 56, -1, -1, -1, -1, -1, -1, -1, -1, -1, -1, -1, -1, -1, 21, -1, -1, -1, -1, -1, 39, 44, -1, -1, -1, -1, -1, 67, 64, 64, 66, -1, -1, -1, -1, -1, -1, -1, -1, -1, -1, 28, 31, -1, -1, -1, -1, 21, -1, -1, -1, -1, -1, -1, -1, -1, -1, -1, -1, -1, -1, -1, -1, -1, -1, -1, -1, -1, -1, -1, -1, -1, -1, -1, 67, 65, 16, 16, 16, 16, 16, 16, 16, 16, 16, 16, 16, 16, 16, 16, 16, 16, 16, 16, 16, 16, 16, 16, 16, 16, 56, -1, -1, -1, -1, -1, -1, -1, -1, -1, -1, -1, -1, -1, -1, -1, -1, -1, -1, -1, 37, -1, -1, -1, -1, -1, 67, 65, 16, 16, 56, -1, -1, -1, -1, -1, -1, -1, -1, -1, -1, 35, -1, -1, -1, -1, 22, -1, -1, -1, -1, -1, -1, -1, -1, -1, -1, -1, -1, -1, -1, -1, -1, -1, -1, -1, -1, -1, -1, -1, -1, -1, -1, 67, 65, 16, 16, 16, 16, 16, 16, 16, 16, 16, 16, 16, 16, 16, 16, 16, 16, 16, 16, 16, 16, 16, 16, 16, 16, 49, 59, -1, -1, -1, -1, -1, -1, -1, -1, -1, -1, -1, -1, -1, -1, -1, -1, -1, -1, 39, 44, -1, -1, -1, -1, 67, 65, 16, 16, 16, 63, 64, 64, 64, 66, -1, -1, 21, -1, -1, -1, 35, -1, -1, -1, -1, 53, -1, -1, -1, -1, -1, -1, -1, -1, -1, -1, -1, -1, -1, -1, -1, -1, -1, -1, -1, -1, 21, -1, -1, -1, 67, 64, 65, 16, 16, 16, 16, 16, 16, 16, 16, 16, 16, 16, 16, 16, 16, 16, 16, 16, 16, 16, 16, 16, 16, 16, 16, 16, 56, -1, -1, -1, -1, -1, -1, -1, -1, -1, -1, -1, -1, 14, -1, -1, -1, -1, -1, -1, 37, -1, -1, -1, -1, -1, 58, 16, 16, 16, 16, 16, 16, 16, 16, 63, 66, -1, -1, -1, -1, 28, 31, -1, -1, -1, -1, -1, -1, -1, -1, -1, -1, -1, 21, -1, -1, 37, -1, -1, 22, -1, 67, 64, 64, 64, 64, 66, -1, 67, 64, 64, 65, 16, 16, 16, 16, 16, 16, 16, 16, 16, 16, 16, 16, 16, 16, 16, 16, 16, 16, 16, 16, 16, 16, 16, 16, 16, 16, 16, 56, 21, -1, -1, 14, -1, -1, -1, 43, 38, 21, 39, 43, 43, 43, 43, 43, 43, 43, 38, 37, -1, -1, -1, -1, -1, 60, 51, 16, 16, 16, 16, 16, 16, 16, 16, 56, -1, -1, -1, -1, 35, -1, -1, -1, -1, -1, -1, -1, -1, -1, 15, -1, -1, -1, -1, -1, 37, -1, -1, -1, -1, 58, 16, 16, 16, 16, 63, 64, 65, 16, 16, 16, 16, 16, 16, 16, 16, 16, 16, 16, 16, 16, 16, 16, 16, 16, 16, 16, 16, 16, 16, 16, 16, 16, 16, 16, 16, 16, 49, 59, -1, -1, -1, -1, -1, -1, -1, -1, 42, 43, 44, -1, -1, -1, -1, -1, -1, -1, 42, 44, -1, -1, -1, -1, -1, -1, 60, 51, 16, 16, 16, 16, 16, 16, 16, 56, -1, -1, -1, -1, -1, -1, -1, -1, -1, -1, -1, -1, -1, -1, -1, -1, -1, -1, -1, -1, 37, -1, -1, -1, -1, 58, 16, 16, 16, 16, 16, 16, 16, 16, 16, 16, 16, 16, 16, 16, 16, 16, 16, 16, 16, 16, 16, 16, 16, 16, 16, 16, 16, 16, 16, 16, 16, 16, 16, 16, 16, 16, 56, -1, -1, -1, -1, -1, -1, -1, -1, -1, -1, -1, -1, -1, -1, -1, -1, -1, -1, -1, -1, -1, -1, -1, -1, -1, -1, -1, -1, 60, 50, 51, 16, 16, 16, 49, 50, 59, -1, -1, -1, -1, -1, -1, -1, -1, -1, -1, -1, -1, -1, -1, -1, -1, -1, -1, -1, 39, 44, -1, -1, -1, -1, 60, 51, 16, 16, 16, 16, 16, 16, 16, 16, 16, 16, 16, 16, 16, 16, 16, 16, 16, 16, 16, 16, 16, 16, 16, 16, 16, 16, 16, 16, 16, 16, 16, 16, 16, 16, 16, 56, -1, -1, -1, -1, -1, -1, -1, -1, -1, -1, -1, -1, -1, -1, -1, -1, -1, -1, -1, -1, -1, -1, -1, -1, -1, -1, -1, -1, -1, -1, 60, 50, 50, 50, 59, -1, -1, -1, -1, -1, -1, -1, -1, -1, -1, -1, -1, -1, -1, -1, -1, -1, -1, -1, -1, -1, 37, -1, -1, -1, -1, -1, -1, 58, 16, 16, 16, 16, 16, 16, 16, 16, 16, 16, 16, 16, 16, 16, 16, 16, 16, 16, 16, 16, 16, 16, 16, 16, 16, 16, 16, 16, 16, 16, 16, 16, 16, 16, 16, 56, -1, -1, -1, -1, -1, -1, -1, -1, -1, -1, -1, -1, -1, -1, -1, -1, -1, -1, -1, -1, -1, -1, -1, -1, -1, -1, -1, -1, -1, 21, -1, -1, -1, -1, -1, -1, -1, -1, -1, -1, -1, -1, -1, 21, 22, -1, -1, -1, 21, -1, -1, -1, -1, -1, 39, 43, 44, -1, -1, -1, -1, -1, -1, 60, 51, 16, 16, 16, 16, 16, 16, 16, 16, 16, 16, 16, 16, 16, 16, 16, 16, 16, 16, 16, 16, 16, 16, 16, 16, 16, 16, 16, 16, 16, 16, 16, 16, 16, 16, 63, 66, 15, -1, -1, -1, -1, -1, -1, -1, 67, 64, 64, 64, 64, 64, 64, 66, 21, -1, -1, -1, -1, -1, -1, -1, -1, -1, 21, -1, -1, -1, -1, -1, -1, -1, -1, -1, -1, -1, -1, -1, -1, -1, 43, 43, 43, 38, -1, -1, 39, 43, 43, 43, 43, 44, -1, -1, -1, 15, -1, -1, 15, -1, -1, 58, 16, 16, 16, 16, 16, 16, 16, 16, 16, 16, 16, 16, 16, 16, 16, 16, 16, 16, 16, 16, 16, 16, 16, 16, 16, 16, 16, 16, 16, 16, 16, 16, 16, 16, 16, 63, 64, 64, 64, 64, 64, 64, 64, 64, 65, 16, 16, 16, 16, 16, 16, 63, 66, -1, -1, -1, -1, -1, -1, -1, -1, -1, -1, -1, -1, -1, -1, -1, -1, -1, 14, -1, -1, -1, -1, -1, -1, -1, -1, -1, -1, 42, 43, 43, 44, -1, -1, -1, 21, -1, -1, -1, -1, -1, -1, -1, -1, -1, -1, 58, 16, 16, 16, 16, 16, 16, 16, 16, 16, 16, 16, 16, 16, 16, 16, 16, 16, 16, 16, 16, 16, 16, 16, 16, 16, 16, 16, 16, 16, 16, 16, 16, 16, 16, 16, 16, 16, 16, 16, 16, 16, 16, 16, 16, 16, 16, 16, 16, 16, 16, 16, 16, 56, -1, -1, -1, -1, -1, -1, -1, -1, -1, -1, -1, -1, -1, -1, -1, -1, -1, -1, -1, -1, -1, -1, -1, -1, -1, -1, -1, -1, -1, -1, 22, -1, -1, -1, -1, -1, -1, -1, -1, -1, -1, -1, -1, -1, -1, -1, 58, 16, 16, 16, 16, 16, 16, 16, 16, 16, 16, 16, 16, 16, 16, 16, 16, 16, 16, 16, 16, 16, 16, 16, 16, 16, 16, 16, 16, 16, 16, 16, 16, 16, 16, 16, 16, 16, 16, 16, 16, 16, 16, 16, 16, 16, 16, 16, 16, 16, 16, 16, 16, 56, -1, -1, -1, -1, -1, -1, -1, -1, -1, -1, -1, -1, -1, -1, -1, -1, -1, -1, -1, -1, -1, -1, -1, -1, 22, 21, -1, -1, -1, -1, -1, -1, -1, -1, -1, -1, -1, -1, -1, -1, -1, -1, -1, -1, 67, 64, 65, 16, 16, 16, 16, 16, 16, 16, 16, 16, 16, 16, 16, 16, 16, 16, 16, 16, 16, 16, 16, 16, 16, 16, 16, 16, 16, 16, 16, 16, 16, 16, 16, 16, 16, 16, 16, 16, 16, 16, 16, 16, 16, 16, 16, 16, 16, 16, 16, 16, 16, 16, 16, 63, 66, -1, -1, -1, -1, -1, -1, -1, -1, 15, -1, -1, -1, -1, -1, -1, -1, -1, -1, -1, -1, -1, -1, -1, -1, -1, -1, -1, -1, 53, -1, -1, -1, -1, 67, 64, 64, 64, 64, 64, 66, -1, -1, 67, 65, 16, 16, 16, 16, 16, 16, 16, 16, 16, 16, 16, 16, 16, 16, 16, 16, 16, 16, 16, 16, 16, 16, 16, 16, 16, 16, 16, 16, 16, 16, 16, 16, 16, 16, 16, 16, 16, 16, 16, 16, 16, 16, 16, 16, 16, 16, 16, 16, 16, 16, 16, 16, 16, 16, 16, 63, 66, -1, -1, -1, -1, -1, -1, -1, -1, -1, -1, -1, -1, -1, -1, -1, -1, -1, -1, -1, -1, -1, -1, -1, -1, -1, -1, 15, -1, -1, -1, 67, 64, 65, 16, 16, 16, 16, 16, 63, 64, 64, 65, 16, 16, 16, 16, 16, 16, 16, 16, 16, 16, 16, 16, 16, 16, 16, 16, 16, 16, 16, 16, 16, 16, 16, 16, 16, 16, 16, 16, 16, 16, 16, 16, 16, 16, 16, 16, 16, 16, 16, 16, 16, 16, 16, 16, 16, 16, 16, 16, 16, 16, 16, 16, 16, 16, 16, 16, 16, 63, 64, 64, 64, 66, -1, -1, -1, -1, -1, -1, -1, -1, -1, -1, -1, -1, -1, -1, -1, -1, -1, -1, -1, -1, -1, -1, -1, -1, -1, -1, 58, 16, 16, 16, 16, 16, 16, 16, 16, 16, 16, 16, 16, 16, 16, 16, 16, 16, 16, 16, 16, 16, 16, 16, 16, 16, 16, 16, 16, 16, 16, 16, 16, 16, 16, 16, 16, 16, 16, 16, 16, 16, 16, 16, 16, 16, 16, 16, 16, 16, 16, 16, 16, 16, 16, 16, 16, 16, 16, 16, 16, 16, 16, 16, 16, 16, 16, 16, 16, 16, 16, 16, 16, 63, 64, 64, 64, 64, 66, -1, -1, -1, -1, -1, -1, -1, -1, -1, -1, -1, -1, -1, -1, -1, -1, -1, -1, -1, -1, -1, 58, 16, 16, 16, 16, 16, 16, 16, 16, 16, 16, 16, 16, 16, 16, 16, 16, 16, 16, 16, 16, 16, 16, 16, 16, 16, 16, 16, 16, 16, 16, 16, 16, 16, 16, 16, 16, 16, 16, 16, 16, 16, 16, 16, 16, 16, 16, 16, 16, 16, 16, 16, 16, 16, 16, 16, 16, 16, 16, 16, 16, 16, 16, 16, 16, 16, 16, 16, 16, 16, 16, 16, 16, 16, 16, 16, 16, 16, 63, 64, 66, -1, -1, -1, 21, -1, -1, 21, -1, -1, -1, -1, -1, -1, -1, -1, 67, 64, 64, 64, 65, 16, 16, 16, 16, 16, 16, 16, 16, 16, 16, 16, 16, 16, 16, 16, 16, 16, 16, 16, 16, 16, 16, 16, 16, 16, 16, 16, 16, 16, 16, 16, 16, 16, 16, 16, 16, 16, 16, 16, 16, 16, 16, 16, 16, 16, 16, 16, 16, 16, 16, 16, 16, 16, 16, 16, 16, 16, 16, 16, 16, 16, 16, 16, 16, 16, 16, 16, 16, 16, 16, 16, 16, 16, 16, 16, 16, 16, 16, 16, 63, 64, 64, 64, 64, 64, 66, -1, 67, 64, 64, 64, 64, 64, 64, 64, 65, 16, 16, 16, 16, 16, 16, 16, 16, 16, 16, 16, 16, 16, 16, 16, 16, 16, 16, 16, 16, 16, 16, 16, 16, 16, 16, 16, 16, 16, 16, 16, 16, 16, 16, 16, 16, 16, 16, 16, 16, 16, 16, 16, 16, 16, 16, 16, 16, 16, 16, 16, 16, 16, 16, 16, 16, 16, 16, 16, 16, 16, 16, 16, 16, 16, 16, 16, 16, 16, 16, 16, 16, 16, 16, 16, 16, 16, 16, 16, 16, 16, 16, 16, 16, 16, 16, 16, 16, 16, 63, 64, 65, 16, 16, 16, 16, 16, 16, 16, 16, 16, 16, 16, 16, 16, 16, 16, 16, 16, 16, 16, 16, 16, 16, 16, 16, 16, 16, 16, 16, 16, 16, 16, 16, 16, 16, 16, 16, 16, 16, 16, 16, 16, 16, 16, 16],
      "exportMode": 0,
      "arrayMode": 0
    },
    {
      "name": "ground",
      "_eid": "84372284",
      "offsetX": 0,
      "offsetY": 0,
      "gridCellWidth": 16,
      "gridCellHeight": 16,
      "gridCellsX": 100,
      "gridCellsY": 54,
      "tileset": "tiles",
      "data": [2, 36, 1, 36, 2, 36, 2, 2, 36, 36, 2, 2, 36, 36, 2, 36, 36, 2, 2, 36, 36, 2, 1, 1, 1, 1, 36, 36, 2, 36, 36, 2, 2, 2, 2, 1, 1, 1, 2, 1, 1, 36, 36, 1, 2, 36, 1, 36, 1, 2, 36, 36, 2, 1, 36, 1, 36, 2, 2, 36, 1, 1, 36, 2, 2, 36, 1, 2, 1, 36, 36, 2, 2, 36, 2, 1, 2, 1, 2, 1, 2, 1, 1, 1, 1, 2, 36, 36, 2, 36, 1, 2, 1, 1, 2, 36, 2, 1, 2, 36, 36, 2, 1, 36, 36, 36, 1, 36, 1, 36, 2, 36, 36, 1, 36, 2, 1, 1, 1, 2, 36, 36, 36, 1, 36, 2, 36, 36, 1, 1, 1, 1, 1, 36, 36, 2, 36, 36, 36, 1, 1, 36, 36, 36, 1, 36, 36, 36, 2, 2, 36, 36, 36, 2, 36, 36, 2, 36, 36, 36, 36, 1, 36, 36, 1, 2, 36, 36, 36, 2, 2, 2, 1, 36, 2, 36, 2, 36, 36, 2, 2, 1, 36, 36, 1, 1, 2, 36, 1, 2, 36, 36, 2, 2, 1, 2, 36, 36, 2, 36, 2, 1, 36, 36, 36, 36, 2, 1, 2, 2, 36, 2, 2, 1, 36, 36, 36, 2, 1, 36, 2, 36, 36, 2, 2, 1, 2, 36, 36, 2, 2, 36, 1, 36, 1, 36, 36, 36, 36, 36, 36, 36, 1, 2, 1, 36, 1, 1, 36, 36, 1, 2, 36, 36, 36, 1, 36, 1, 36, 36, 1, 36, 36, 36, 1, 2, 36, 36, 36, 36, 36, 36, 36, 36, 1, 1, 36, 1, 36, 1, 2, 1, 2, 2, 36, 2, 1, 36, 1, 36, 36, 1, 36, 36, 36, 1, 36, 1, 1, 2, 36, 36, 36, 36, 36, 2, 1, 36, 36, 36, 1, 2, 2, 1, 2, 36, 2, 1, 1, 36, 1, 36, 36, 36, 36, 36, 2, 36, 2, 2, 36, 1, 36, 36, 2, 2, 36, 2, 36, 36, 2, 1, 36, 36, 36, 2, 36, 36, 36, 36, 36, 1, 36, 36, 36, 2, 2, 36, 1, 1, 36, 2, 36, 2, 36, 36, 2, 36, 2, 36, 36, 36, 36, 36, 36, 2, 2, 36, 36, 1, 36, 36, 1, 36, 2, 2, 1, 36, 1, 2, 1, 36, 2, 1, 36, 36, 36, 36, 1, 2, 2, 36, 1, 1, 36, 2, 2, 2, 2, 36, 36, 36, 36, 1, 36, 36, 36, 2, 36, 2, 36, 1, 1, 36, 36, 2, 36, 1, 2, 1, 1, 36, 36, 36, 36, 1, 36, 36, 36, 1, 36, 2, 36, 36, 36, 1, 1, 2, 2, 36, 36, 2, 36, 1, 2, 36, 2, 1, 1, 2, 1, 1, 36, 36, 2, 36, 2, 1, 36, 1, 1, 1, 36, 36, 36, 2, 36, 36, 1, 36, 1, 2, 36, 1, 2, 2, 36, 2, 36, 36, 36, 36, 36, 2, 2, 36, 36, 2, 2, 2, 1, 36, 36, 1, 1, 1, 36, 2, 36, 2, 36, 36, 36, 2, 36, 1, 2, 1, 2, 2, 1, 36, 2, 36, 36, 1, 36, 36, 36, 1, 1, 2, 1, 36, 36, 1, 1, 36, 1, 36, 2, 2, 1, 1, 36, 36, 36, 2, 36, 2, 36, 1, 2, 2, 2, 2, 36, 36, 1, 36, 1, 1, 2, 2, 36, 2, 36, 36, 1, 36, 1, 1, 2, 36, 1, 2, 2, 1, 2, 2, 36, 1, 36, 1, 2, 36, 36, 2, 2, 2, 1, 36, 1, 36, 2, 2, 36, 36, 1, 1, 36, 36, 1, 36, 2, 36, 1, 36, 36, 36, 2, 2, 36, 2, 1, 36, 36, 36, 2, 36, 2, 2, 2, 1, 36, 1, 36, 1, 2, 2, 1, 36, 2, 2, 36, 36, 2, 36, 36, 1, 36, 36, 2, 2, 36, 36, 2, 36, 1, 2, 36, 36, 1, 36, 36, 36, 1, 36, 36, 1, 36, 2, 36, 36, 1, 1, 36, 36, 1, 36, 1, 1, 2, 2, 36, 36, 1, 36, 2, 2, 1, 2, 2, 1, 2, 36, 1, 2, 36, 36, 36, 36, 36, 2, 2, 36, 36, 36, 36, 36, 36, 1, 2, 36, 36, 2, 36, 1, 36, 1, 2, 36, 1, 36, 2, 36, 36, 2, 2, 2, 36, 2, 1, 36, 36, 36, 2, 2, 36, 36, 36, 36, 1, 2, 1, 1, 1, 36, 1, 36, 36, 36, 2, 36, 2, 1, 2, 1, 1, 36, 36, 1, 1, 1, 36, 1, 36, 36, 2, 36, 2, 2, 1, 36, 2, 2, 2, 2, 2, 1, 36, 36, 36, 2, 36, 36, 2, 36, 36, 36, 2, 36, 1, 36, 2, 2, 36, 36, 1, 2, 2, 36, 2, 2, 2, 36, 1, 1, 2, 36, 36, 1, 36, 36, 1, 36, 2, 36, 1, 36, 36, 36, 1, 2, 2, 1, 2, 36, 2, 1, 1, 36, 36, 36, 36, 36, 36, 1, 36, 36, 2, 1, 2, 2, 36, 1, 1, 1, 36, 1, 1, 36, 1, 36, 36, 1, 36, 36, 2, 36, 36, 36, 1, 2, 36, 2, 1, 36, 36, 1, 36, 36, 1, 1, 1, 1, 2, 36, 2, 2, 2, 2, 2, 36, 1, 36, 36, 1, 1, 36, 1, 2, 36, 36, 1, 36, 36, 1, 1, 36, 36, 36, 2, 36, 36, 2, 36, 36, 2, 36, 2, 1, 2, 36, 2, 36, 2, 36, 2, 36, 36, 36, 36, 1, 36, 36, 2, 36, 2, 1, 2, 36, 1, 36, 36, 1, 36, 1, 1, 36, 36, 1, 2, 2, 36, 1, 36, 1, 36, 36, 1, 2, 1, 1, 1, 1, 1, 2, 2, 36, 2, 36, 2, 2, 36, 36, 1, 36, 36, 36, 36, 36, 1, 1, 2, 2, 2, 2, 1, 36, 36, 36, 2, 36, 1, 36, 2, 1, 2, 1, 36, 2, 36, 36, 1, 2, 36, 36, 36, 36, 1, 1, 36, 36, 2, 36, 36, 36, 36, 36, 36, 36, 1, 2, 36, 36, 36, 36, 1, 36, 2, 36, 36, 36, 36, 36, 36, 36, 36, 36, 36, 1, 2, 36, 36, 2, 36, 36, 36, 36, 36, 2, 1, 1, 36, 2, 1, 36, 2, 1, 36, 1, 2, 2, 1, 1, 1, 2, 36, 2, 36, 36, 1, 1, 2, 36, 2, 36, 2, 36, 36, 2, 2, 2, 36, 1, 2, 36, 36, 2, 1, 36, 36, 36, 36, 36, 1, 36, 36, 1, 36, 36, 2, 1, 1, 36, 1, 36, 1, 2, 1, 36, 1, 36, 1, 2, 36, 2, 2, 1, 36, 2, 36, 36, 2, 36, 36, 1, 1, 2, 36, 1, 36, 1, 1, 2, 36, 1, 36, 2, 1, 36, 36, 1, 2, 1, 36, 36, 36, 36, 36, 36, 2, 36, 36, 1, 36, 2, 36, 2, 36, 36, 36, 2, 36, 2, 36, 2, 36, 36, 1, 36, 36, 36, 1, 36, 2, 36, 36, 1, 36, 1, 1, 1, 1, 36, 36, 2, 36, 36, 36, 2, 1, 36, 1, 36, 36, 36, 36, 1, 36, 36, 36, 2, 36, 36, 1, 2, 36, 2, 36, 1, 1, 36, 36, 2, 36, 36, 2, 2, 36, 36, 36, 1, 36, 36, 2, 36, 1, 36, 2, 36, 36, 1, 36, 36, 2, 36, 36, 36, 36, 1, 2, 2, 36, 1, 2, 36, 1, 1, 1, 36, 36, 36, 36, 36, 36, 1, 36, 36, 1, 36, 36, 36, 1, 1, 2, 36, 36, 36, 1, 36, 36, 36, 36, 36, 2, 36, 36, 36, 1, 36, 36, 36, 36, 1, 36, 36, 2, 36, 2, 36, 36, 36, 36, 36, 1, 36, 36, 36, 36, 2, 36, 36, 2, 36, 1, 36, 36, 2, 1, 36, 36, 1, 2, 2, 1, 36, 36, 36, 1, 36, 1, 1, 36, 1, 2, 1, 2, 36, 36, 1, 36, 1, 1, 2, 2, 1, 36, 36, 36, 1, 2, 36, 2, 36, 36, 36, 2, 36, 36, 36, 2, 2, 36, 36, 2, 2, 36, 1, 36, 36, 1, 36, 2, 36, 36, 36, 1, 36, 36, 36, 2, 36, 2, 36, 1, 36, 36, 2, 1, 2, 1, 36, 1, 36, 36, 36, 36, 36, 36, 36, 36, 1, 36, 36, 36, 2, 1, 1, 36, 36, 2, 36, 36, 2, 36, 2, 2, 36, 2, 1, 36, 36, 2, 36, 1, 1, 36, 2, 2, 36, 36, 2, 36, 1, 2, 1, 36, 2, 36, 36, 36, 36, 36, 36, 2, 36, 36, 36, 36, 36, 2, 36, 36, 36, 1, 2, 36, 36, 2, 2, 36, 2, 36, 36, 2, 36, 1, 2, 36, 1, 36, 36, 1, 2, 2, 36, 2, 1, 36, 36, 2, 36, 2, 36, 36, 1, 36, 36, 1, 36, 36, 36, 36, 2, 36, 2, 36, 2, 36, 36, 2, 1, 36, 2, 1, 36, 36, 36, 36, 1, 2, 36, 36, 36, 1, 1, 1, 2, 36, 2, 2, 1, 36, 1, 36, 2, 2, 36, 36, 36, 36, 36, 1, 36, 36, 36, 1, 36, 2, 36, 2, 36, 2, 1, 2, 2, 36, 36, 2, 2, 36, 36, 1, 36, 36, 36, 1, 36, 36, 36, 1, 36, 1, 36, 36, 36, 2, 1, 2, 2, 1, 1, 2, 1, 1, 36, 1, 2, 1, 1, 2, 36, 36, 2, 2, 36, 36, 2, 36, 2, 36, 2, 36, 36, 36, 36, 2, 2, 36, 36, 1, 36, 36, 2, 36, 2, 36, 1, 1, 1, 1, 2, 36, 36, 36, 1, 36, 1, 2, 2, 36, 36, 36, 36, 36, 36, 36, 36, 2, 1, 36, 2, 1, 1, 2, 36, 36, 36, 36, 2, 36, 36, 36, 36, 36, 36, 2, 36, 36, 2, 36, 2, 1, 36, 1, 1, 36, 2, 36, 2, 1, 1, 1, 36, 36, 36, 2, 36, 2, 36, 36, 36, 1, 36, 2, 1, 2, 2, 36, 36, 36, 36, 1, 1, 2, 1, 36, 2, 36, 36, 2, 36, 2, 1, 36, 2, 36, 36, 2, 1, 36, 2, 2, 1, 1, 2, 1, 36, 36, 36, 1, 2, 2, 36, 2, 36, 36, 36, 36, 36, 36, 36, 1, 1, 36, 36, 36, 2, 2, 1, 2, 36, 1, 1, 1, 36, 2, 2, 2, 36, 1, 36, 36, 2, 2, 1, 1, 36, 36, 36, 1, 36, 1, 1, 36, 36, 36, 36, 2, 1, 1, 1, 36, 36, 36, 2, 1, 1, 36, 36, 2, 2, 1, 2, 1, 36, 36, 1, 36, 36, 36, 2, 1, 1, 2, 2, 36, 1, 1, 2, 2, 36, 36, 36, 36, 2, 36, 1, 2, 2, 2, 36, 2, 1, 2, 36, 36, 1, 2, 1, 36, 36, 36, 36, 2, 36, 2, 1, 1, 36, 36, 36, 2, 36, 1, 36, 1, 36, 1, 1, 1, 36, 36, 2, 2, 36, 2, 36, 2, 1, 36, 36, 2, 2, 36, 36, 36, 36, 1, 2, 1, 36, 2, 36, 2, 36, 36, 2, 1, 36, 2, 1, 36, 36, 1, 36, 36, 36, 2, 36, 2, 2, 36, 36, 36, 36, 36, 36, 2, 2, 1, 36, 36, 36, 36, 36, 1, 36, 2, 1, 36, 36, 1, 36, 1, 36, 36, 36, 1, 1, 2, 36, 36, 36, 36, 1, 36, 2, 36, 1, 36, 2, 36, 2, 1, 36, 36, 2, 2, 36, 36, 36, 1, 2, 36, 2, 2, 36, 36, 36, 36, 1, 2, 36, 36, 36, 2, 2, 36, 1, 1, 36, 1, 36, 2, 2, 36, 2, 36, 1, 2, 2, 2, 36, 36, 1, 36, 2, 2, 2, 2, 36, 2, 1, 2, 1, 1, 36, 36, 36, 2, 36, 36, 1, 1, 36, 36, 36, 36, 36, 2, 36, 36, 1, 36, 2, 36, 1, 1, 1, 36, 2, 36, 1, 36, 1, 36, 2, 2, 36, 1, 1, 2, 2, 1, 1, 1, 2, 1, 2, 2, 36, 36, 36, 36, 36, 36, 36, 1, 1, 36, 2, 36, 36, 36, 1, 36, 1, 2, 2, 2, 1, 36, 36, 36, 1, 36, 36, 36, 2, 36, 1, 2, 36, 1, 1, 2, 36, 36, 36, 36, 36, 1, 1, 36, 36, 2, 2, 2, 1, 36, 1, 1, 1, 1, 36, 1, 2, 1, 2, 1, 36, 36, 1, 36, 36, 2, 1, 1, 1, 1, 36, 36, 36, 36, 2, 1, 36, 1, 2, 36, 36, 1, 36, 2, 36, 36, 36, 2, 2, 2, 36, 36, 2, 36, 2, 36, 2, 36, 36, 36, 36, 36, 2, 1, 2, 2, 36, 2, 1, 36, 36, 36, 36, 2, 36, 36, 1, 2, 36, 36, 1, 36, 1, 1, 2, 2, 1, 2, 2, 2, 1, 36, 2, 1, 2, 36, 2, 1, 36, 1, 1, 2, 2, 2, 36, 1, 2, 2, 2, 2, 2, 36, 2, 36, 1, 36, 2, 36, 36, 1, 36, 36, 36, 36, 1, 36, 2, 2, 36, 36, 2, 36, 2, 36, 36, 1, 2, 36, 2, 1, 1, 36, 2, 36, 36, 1, 36, 1, 36, 36, 1, 2, 1, 36, 36, 1, 2, 2, 36, 2, 36, 2, 2, 36, 36, 36, 1, 36, 36, 36, 36, 1, 1, 36, 2, 1, 36, 2, 1, 2, 2, 1, 36, 1, 2, 36, 36, 36, 2, 36, 1, 36, 2, 1, 36, 1, 1, 2, 36, 2, 1, 1, 1, 2, 36, 36, 36, 2, 36, 36, 2, 2, 36, 1, 1, 2, 36, 1, 1, 1, 36, 36, 2, 1, 36, 1, 36, 36, 1, 2, 36, 2, 36, 2, 36, 36, 1, 1, 1, 36, 2, 36, 36, 36, 36, 2, 36, 1, 36, 36, 1, 36, 1, 2, 2, 2, 2, 36, 36, 2, 36, 36, 2, 1, 1, 2, 2, 36, 1, 36, 1, 1, 36, 36, 36, 36, 2, 36, 36, 36, 36, 36, 36, 36, 1, 36, 36, 1, 36, 2, 2, 36, 2, 2, 2, 1, 36, 2, 36, 36, 36, 36, 36, 36, 2, 1, 36, 1, 1, 36, 2, 36, 2, 1, 1, 36, 2, 36, 36, 1, 1, 2, 36, 1, 2, 36, 2, 36, 36, 36, 1, 1, 36, 36, 36, 36, 36, 36, 36, 36, 36, 36, 1, 36, 1, 36, 2, 2, 36, 2, 1, 36, 36, 36, 36, 2, 36, 1, 36, 36, 36, 36, 2, 36, 2, 1, 36, 1, 36, 36, 1, 2, 36, 36, 36, 36, 36, 36, 1, 2, 2, 1, 1, 2, 2, 1, 1, 36, 1, 2, 1, 2, 2, 36, 36, 36, 1, 36, 36, 1, 36, 2, 1, 2, 1, 36, 1, 1, 36, 36, 1, 2, 36, 1, 36, 1, 2, 2, 1, 1, 1, 36, 36, 36, 36, 36, 36, 36, 2, 2, 2, 2, 36, 36, 36, 36, 1, 2, 36, 36, 36, 36, 36, 36, 1, 2, 36, 36, 1, 2, 2, 36, 1, 2, 1, 36, 36, 36, 36, 36, 2, 36, 1, 2, 36, 1, 36, 1, 36, 2, 1, 1, 1, 36, 2, 2, 36, 1, 1, 36, 36, 2, 1, 1, 1, 2, 36, 36, 2, 36, 1, 36, 36, 36, 2, 2, 1, 36, 36, 36, 36, 36, 36, 36, 2, 2, 1, 36, 1, 36, 36, 2, 1, 36, 1, 36, 2, 36, 36, 1, 1, 36, 36, 1, 2, 1, 2, 1, 36, 1, 2, 1, 36, 36, 1, 36, 2, 1, 36, 36, 1, 2, 36, 36, 1, 1, 2, 2, 36, 1, 36, 36, 36, 1, 36, 36, 36, 36, 1, 36, 36, 2, 2, 36, 36, 36, 2, 36, 36, 36, 36, 36, 36, 2, 2, 1, 36, 1, 2, 36, 2, 2, 2, 36, 1, 2, 2, 36, 1, 36, 2, 1, 2, 36, 36, 36, 2, 36, 1, 2, 2, 1, 36, 1, 1, 36, 36, 2, 2, 36, 36, 36, 36, 36, 2, 36, 36, 1, 2, 2, 1, 2, 1, 1, 1, 2, 36, 1, 36, 2, 2, 36, 36, 36, 1, 36, 36, 1, 36, 1, 36, 36, 36, 36, 1, 36, 36, 2, 36, 36, 36, 1, 36, 36, 2, 36, 36, 36, 1, 36, 2, 2, 36, 2, 36, 36, 1, 36, 2, 36, 36, 36, 36, 1, 36, 36, 36, 2, 1, 36, 36, 36, 36, 2, 36, 1, 1, 2, 36, 1, 36, 36, 36, 36, 36, 2, 36, 2, 36, 2, 36, 1, 36, 1, 36, 1, 2, 1, 36, 36, 36, 36, 36, 36, 36, 1, 1, 1, 1, 36, 1, 36, 1, 36, 36, 1, 36, 2, 1, 2, 2, 1, 1, 2, 36, 36, 2, 1, 2, 36, 36, 36, 1, 1, 36, 36, 2, 36, 36, 36, 2, 2, 36, 2, 36, 1, 36, 2, 36, 36, 1, 1, 1, 36, 2, 2, 36, 1, 36, 1, 1, 2, 36, 36, 1, 36, 2, 2, 36, 1, 2, 36, 36, 36, 36, 2, 2, 1, 36, 2, 1, 2, 36, 36, 1, 2, 2, 2, 1, 36, 36, 1, 36, 36, 1, 36, 2, 1, 1, 36, 36, 36, 36, 2, 1, 36, 36, 36, 36, 1, 36, 36, 1, 1, 1, 36, 2, 2, 36, 36, 36, 36, 1, 2, 2, 2, 2, 36, 36, 1, 36, 2, 2, 36, 2, 36, 36, 1, 2, 36, 2, 36, 2, 36, 2, 36, 1, 36, 1, 2, 36, 36, 1, 36, 2, 1, 2, 1, 36, 2, 2, 36, 2, 2, 1, 1, 1, 2, 2, 36, 36, 36, 2, 36, 1, 1, 1, 36, 36, 2, 2, 36, 36, 36, 2, 2, 1, 2, 36, 2, 1, 2, 1, 36, 36, 1, 1, 36, 2, 36, 36, 36, 1, 36, 1, 36, 1, 1, 2, 1, 36, 36, 2, 36, 1, 2, 36, 2, 36, 1, 36, 36, 36, 2, 36, 2, 1, 2, 36, 1, 1, 2, 36, 36, 36, 2, 36, 36, 36, 2, 36, 2, 36, 36, 36, 36, 2, 36, 2, 36, 36, 36, 2, 36, 36, 36, 1, 2, 36, 36, 36, 1, 36, 1, 1, 36, 2, 36, 1, 1, 2, 36, 1, 1, 36, 2, 1, 2, 1, 2, 1, 2, 1, 1, 36, 36, 36, 36, 2, 1, 1, 2, 1, 2, 36, 1, 36, 1, 36, 36, 1, 36, 36, 2, 1, 2, 1, 36, 36, 36, 1, 1, 2, 36, 36, 2, 2, 1, 36, 36, 2, 36, 36, 2, 36, 2, 36, 2, 2, 2, 2, 36, 1, 36, 36, 36, 1, 36, 2, 36, 1, 1, 2, 2, 2, 2, 1, 1, 1, 2, 1, 36, 36, 2, 36, 36, 36, 2, 2, 36, 2, 2, 2, 2, 1, 2, 36, 1, 36, 1, 2, 1, 36, 36, 1, 36, 1, 36, 36, 2, 36, 36, 1, 2, 2, 36, 2, 2, 36, 1, 1, 36, 36, 1, 1, 1, 1, 36, 36, 2, 36, 36, 2, 2, 36, 36, 2, 2, 36, 2, 36, 36, 2, 36, 2, 1, 36, 36, 1, 36, 36, 36, 36, 1, 2, 2, 1, 2, 36, 36, 36, 1, 1, 2, 36, 36, 1, 36, 36, 36, 2, 1, 2, 1, 36, 1, 36, 2, 36, 36, 2, 36, 1, 2, 2, 1, 2, 36, 36, 1, 36, 36, 1, 2, 36, 36, 2, 36, 2, 36, 36, 36, 36, 2, 36, 36, 36, 1, 1, 2, 1, 36, 36, 36, 1, 2, 36, 2, 1, 2, 1, 36, 2, 2, 1, 36, 36, 36, 36, 36, 2, 1, 2, 2, 2, 1, 2, 2, 2, 36, 2, 2, 36, 2, 1, 2, 2, 1, 2, 36, 36, 36, 36, 36, 36, 36, 1, 1, 2, 2, 1, 36, 1, 36, 1, 36, 36, 2, 36, 36, 1, 36, 36, 2, 36, 2, 36, 1, 1, 36, 36, 1, 2, 36, 2, 2, 36, 36, 1, 36, 1, 2, 36, 2, 2, 2, 2, 2, 36, 36, 2, 36, 2, 2, 36, 1, 2, 36, 2, 36, 1, 36, 36, 36, 36, 36, 1, 2, 2, 1, 2, 2, 1, 1, 36, 36, 1, 1, 2, 36, 36, 36, 2, 2, 36, 36, 36, 2, 1, 36, 36, 36, 2, 2, 2, 36, 36, 2, 36, 36, 36, 1, 2, 36, 36, 36, 2, 1, 1, 36, 36, 36, 2, 36, 36, 1, 2, 2, 1, 36, 2, 36, 2, 2, 36, 36, 1, 2, 36, 36, 36, 1, 2, 2, 36, 2, 36, 2, 36, 36, 1, 2, 36, 36, 2, 36, 1, 2, 36, 36, 2, 36, 2, 1, 2, 36, 36, 1, 1, 36, 1, 2, 1, 36, 2, 2, 2, 36, 36, 36, 36, 2, 36, 36, 1, 2, 1, 36, 36, 2, 2, 1, 36, 2, 36, 2, 2, 1, 1, 2, 36, 36, 36, 1, 36, 36, 36, 1, 36, 2, 2, 36, 2, 36, 36, 1, 2, 1, 1, 1, 36, 36, 36, 1, 2, 36, 1, 1, 36, 36, 2, 1, 36, 1, 36, 36, 36, 36, 2, 1, 36, 36, 2, 36, 2, 1, 36, 36, 36, 2, 36, 1, 2, 1, 1, 1, 36, 36, 2, 2, 1, 36, 2, 36, 1, 36, 2, 36, 36, 1, 1, 36, 36, 36, 2, 36, 36, 2, 2, 1, 36, 36, 36, 36, 36, 2, 1, 1, 2, 1, 36, 1, 1, 1, 1, 1, 1, 36, 36, 36, 1, 36, 36, 36, 2, 2, 36, 36, 36, 2, 36, 1, 36, 36, 2, 36, 1, 36, 2, 1, 36, 36, 2, 1, 2, 36, 2, 1, 1, 1, 2, 1, 1, 36, 36, 36, 36, 1, 2, 36, 36, 36, 1, 36, 2, 36, 36, 36, 36, 36, 36, 1, 2, 36, 1, 1, 1, 36, 1, 1, 1, 1, 2, 2, 1, 36, 2, 36, 36, 36, 36, 2, 36, 2, 2, 2, 36, 2, 1, 36, 36, 36, 1, 2, 2, 36, 2, 36, 36, 36, 1, 1, 2, 1, 1, 36, 1, 36, 36, 2, 36, 36, 36, 1, 2, 36, 1, 36, 36, 36, 1, 36, 36, 2, 2, 2, 1, 2, 2, 1, 36, 36, 36, 2, 36, 2, 1, 36, 1, 36, 2, 36, 36, 36, 1, 2, 2, 1, 1, 1, 36, 36, 36, 36, 2, 1, 36, 36, 36, 1, 36, 2, 36, 36, 1, 36, 1, 2, 2, 36, 1, 2, 2, 1, 1, 36, 1, 36, 1, 36, 36, 1, 36, 36, 1, 1, 2, 2, 36, 36, 36, 2, 2, 36, 2, 2, 36, 36, 2, 36, 2, 2, 1, 36, 36, 2, 2, 36, 1, 2, 2, 36, 2, 36, 2, 36, 2, 1, 36, 36, 1, 2, 36, 1, 36, 1, 36, 36, 2, 36, 36, 1, 36, 1, 2, 36, 36, 1, 1, 36, 36, 36, 2, 1, 1, 36, 36, 36, 2, 36, 36, 1, 36, 36, 1, 1, 36, 1, 2, 36, 1, 1, 1, 36, 36, 2, 2, 36, 36, 2, 2, 36, 2, 36, 36, 36, 1, 36, 36, 2, 1, 36, 1, 36, 36, 1, 36, 36, 36, 1, 36, 2, 36, 36, 1, 36, 2, 36, 36, 1, 36, 36, 2, 1, 1, 36, 2, 2, 2, 1, 36, 36, 2, 36, 36, 36, 36, 36, 2, 36, 36, 36, 36, 1, 36, 1, 2, 36, 1, 2, 36, 36, 1, 1, 2, 2, 36, 36, 2, 2, 2, 1, 1, 2, 36, 36, 36, 36, 1, 2, 36, 1, 36, 1, 36, 1, 1, 1, 2, 36, 36, 36, 2, 2, 1, 36, 36, 36, 2, 36, 2, 36, 1, 36, 1, 36, 36, 1, 1, 1, 36, 36, 2, 36, 2, 1, 2, 2, 2, 36, 2, 36, 36, 2, 36, 2, 1, 1, 2, 2, 36, 1, 2, 36, 1, 36, 36, 1, 2, 36, 1, 2, 1, 36, 2, 2, 2, 36, 36, 36, 36, 36, 36, 36, 1, 2, 36, 36, 36, 36, 1, 1, 2, 36, 36, 36, 1, 36, 1, 2, 1, 2, 36, 1, 36, 36, 2, 36, 2, 1, 2, 1, 2, 36, 36, 36, 36, 36, 36, 36, 1, 36, 2, 36, 36, 1, 2, 36, 36, 36, 2, 2, 1, 36, 1, 1, 2, 1, 1, 36, 36, 36, 36, 2, 2, 1, 36, 36, 2, 36, 36, 36, 36, 36, 2, 2, 36, 36, 36, 2, 36, 36, 36, 2, 36, 36, 1, 36, 2, 1, 36, 36, 1, 2, 1, 36, 2, 1, 2, 36, 2, 2, 1, 36, 36, 2, 2, 36, 36, 36, 36, 36, 36, 2, 1, 1, 1, 1, 36, 1, 36, 36, 2, 36, 36, 36, 2, 1, 2, 36, 36, 2, 1, 36, 36, 2, 2, 36, 1, 36, 2, 36, 36, 36, 2, 1, 2, 2, 1, 36, 2, 36, 36, 1, 1, 1, 2, 36, 36, 36, 36, 36, 36, 2, 2, 36, 2, 1, 36, 2, 36, 1, 2, 36, 36, 36, 36, 1, 2, 1, 2, 2, 1, 36, 36, 2, 2, 2, 2, 1, 2, 2, 2, 36, 1, 36, 36, 36, 2, 36, 2, 1, 1, 36, 36, 36, 2, 1, 36, 1, 2, 36, 1, 1, 1, 36, 2, 36, 1, 2, 2, 1, 2, 36, 36, 36, 36, 36, 1, 36, 2, 36, 36, 36, 36, 36, 36, 2, 36, 36, 36, 2, 1, 2, 1, 36, 36, 36, 2, 36, 36, 36, 1, 36, 36, 2, 1, 1, 2, 36, 36, 1, 1, 36, 36, 36, 36, 36, 1, 36, 36, 36, 36, 36, 2, 36, 2, 36, 36, 1, 1, 1, 36, 36, 36, 1, 1, 36, 36, 1, 36, 36, 2, 36, 36, 36, 1, 36, 1, 1, 1, 36, 36, 2, 36, 36, 36, 2, 1, 36, 1, 1, 36, 36, 1, 2, 36, 36, 36, 36, 36, 1, 36, 36, 36, 1, 1, 1, 36, 2, 2, 2, 2, 2, 2, 36, 36, 1, 2, 1, 36, 1, 2, 1, 2, 2, 36, 36, 36, 36, 1, 36, 2, 36, 1, 36, 36, 36, 2, 1, 36, 36, 36, 36, 1, 1, 1, 2, 36, 36, 1, 1, 36, 1, 2, 2, 36, 1, 2, 36, 36, 2, 36, 2, 36, 1, 36, 1, 36, 36, 2, 36, 36, 36, 1, 2, 2, 36, 1, 36, 36, 36, 36, 1, 2, 36, 1, 1, 2, 2, 36, 36, 2, 36, 36, 36, 36, 36, 1, 1, 36, 1, 36, 1, 1, 36, 36, 36, 36, 36, 1, 36, 2, 36, 36, 1, 36, 36, 36, 36, 2, 36, 2, 1, 36, 36, 1, 1, 2, 1, 2, 36, 36, 36, 36, 36, 36, 2, 36, 1, 36, 36, 2, 1, 2, 36, 1, 1, 36, 36, 36, 36, 36, 36, 36, 1, 1, 1, 2, 2, 2, 1, 36, 2, 36, 36, 1, 36, 36, 1, 1, 36, 2, 2, 1, 1, 2, 2, 1, 1, 36, 1, 36, 36, 36, 1, 2, 1, 2, 2, 1, 36, 1, 36, 36, 2, 36, 36, 36, 36, 2, 1, 2, 1, 1, 36, 1, 1, 36, 2, 1, 1, 1, 1, 2, 36, 36, 2, 1, 36, 36, 2, 2, 1, 36, 2, 1, 2, 2, 36, 2, 36, 1, 36, 36, 36, 36, 2, 2, 36, 1, 2, 1, 2, 36, 2, 2, 36, 36, 2, 2, 36, 36, 36, 36, 2, 36, 36, 36, 1, 36, 2, 36, 36, 2, 1, 36, 36, 36, 2, 36, 36, 36, 2, 1, 36, 2, 36, 2, 2, 1, 36, 1, 1, 2, 36, 36, 2, 2, 36, 36, 36, 2, 36, 36, 2, 36, 2, 2, 36, 2, 36, 36, 36, 1, 36, 1, 36, 2, 1, 36, 36, 1, 36, 1, 1, 1, 1, 36, 2, 1, 36, 36, 36, 2, 36, 2, 36, 36, 2, 1, 1, 2, 1, 36, 2, 36, 36, 2, 1, 2, 36, 36, 1, 36, 36, 1, 1, 36, 36, 36, 2, 36, 36, 1, 36, 36, 36, 1, 36, 1, 2, 36, 36, 36, 36, 2, 2, 2, 1, 36, 2, 36, 36, 36, 36, 1, 36, 36, 36, 1, 36, 2, 2, 36, 2, 36, 36, 1, 1, 2, 36, 2, 1, 36, 36, 1, 36, 2, 1, 36, 36, 2, 1, 1, 1, 36, 36, 36, 36, 36, 36, 2, 1, 36, 1, 36, 36, 1, 2, 36, 36, 2, 36, 36, 36, 36, 2, 36, 2, 2, 36, 36, 36, 36, 1, 1, 36, 2, 1, 2, 36, 36, 36, 36, 36, 36, 36, 36, 1, 1, 2, 2, 36, 1, 1, 36, 36, 1, 36, 1, 1, 36, 36, 2, 36, 36, 1, 2, 36, 36, 36, 2, 1, 2, 36, 2, 36, 1, 1, 36, 1, 1, 36, 2, 1, 1, 36, 1, 36, 36, 2, 1, 1, 2, 36, 36, 36, 2, 1, 36, 36, 36, 2, 36, 36, 1, 36, 36, 36, 36, 2, 2, 36, 36, 1, 2, 36, 36, 2, 2, 1, 1, 1, 36, 36, 1, 36, 2, 1, 36, 2, 2, 36, 36, 2, 1, 36, 1, 36, 1, 2, 2, 36, 36, 1, 1, 2, 1, 1, 36, 1, 36, 2, 2, 2, 36, 2, 2, 36, 2, 36, 36, 2, 2, 36, 2, 36, 36, 36, 36, 1, 2, 36, 36, 36, 2, 2, 1, 2, 36, 36, 1, 2, 36, 36, 1, 2, 2, 36, 36, 36, 2, 36, 36, 2, 36, 2, 36, 2, 2, 2, 2, 36, 2, 36, 36, 1, 36, 36, 1, 2, 36, 36, 1, 36, 1, 36, 36, 36, 36, 2, 1, 2, 1, 36, 36, 1, 36, 36, 1, 36, 2, 36, 1, 1, 2, 36, 36, 36, 2, 36, 2, 1, 36, 36, 36, 2, 36, 36, 1, 36, 2, 36, 2, 36, 36, 36, 36, 36, 1, 36, 36, 2, 36, 1, 2, 1, 1, 36, 2, 36, 36, 36, 36, 2, 1, 36, 2, 1, 2, 2, 36, 1, 36, 36, 2, 1, 36, 36, 36, 2, 36, 1, 2, 36, 2, 36, 36, 1, 36, 36, 36, 2, 36, 1, 36, 36, 36, 36, 36, 2, 2, 36, 36, 36, 2, 1, 2, 1, 36, 1, 36, 36, 1, 36, 36, 2, 1, 1, 36, 1, 1, 36, 36, 1, 36, 36, 36, 36, 2, 2, 36, 2, 1, 36, 36, 2, 2, 2, 1, 36, 2, 36, 1, 36, 1, 36, 1, 36, 2, 2, 2, 36, 1, 36, 2, 1, 1, 36, 36, 2, 2, 36, 2, 1, 36, 1, 2, 2, 36, 2, 2, 1, 2, 36, 36, 1, 36, 2, 2, 36, 1, 1, 36, 36, 36, 36, 36, 36, 2, 1, 36, 2, 1, 1, 1, 2, 1, 2, 36, 36, 36, 1, 1, 36, 36, 2, 2, 36, 36, 1, 1, 36, 2, 36, 36, 1, 1, 2, 1, 36, 1, 36, 36, 1, 36, 36, 1, 36, 2, 36, 1, 1, 36, 2, 36, 36, 36, 36, 36, 2, 1, 2, 36, 36, 1, 2, 36, 36, 36, 2, 36, 36, 2, 2, 2, 36, 36, 2, 2, 1, 2, 2, 2, 2, 2, 1, 2, 2, 36, 36, 36, 36, 2, 1, 36, 2, 36, 1, 36, 36, 36, 36, 36, 2, 2, 1, 2, 1, 36, 36, 2, 36, 36, 2, 36, 36, 1, 1, 1, 36, 2, 2, 36, 36, 36, 36, 2, 1, 36, 36, 36, 2, 2, 2, 36, 36, 1, 1, 2, 36, 1, 36, 36, 1, 36, 1, 2, 36, 2, 36, 36, 1, 1, 36, 2, 36, 1, 2, 2, 1, 36, 36, 36, 2, 36, 2, 2, 36, 36, 2, 36, 36, 36, 36, 36, 1, 36, 1, 1, 1, 36, 2, 36, 1, 36, 2, 36, 36, 36, 1, 2, 36, 36, 2, 36, 36, 2, 1, 1, 2, 2, 1, 36, 2, 36, 2, 36, 2, 1, 2, 36, 36, 1, 2, 2, 36, 36, 1, 1, 36, 2, 1, 2, 2, 2, 36, 36, 1, 2, 1, 36, 2, 1, 36, 36, 36, 36, 1, 36, 36, 2, 36, 2, 36, 36, 36, 36, 1, 2, 36, 36, 36, 36, 1, 1, 36, 2, 36, 36, 36, 36, 1, 36, 36, 36, 36, 36, 36, 36, 1, 2, 36, 36, 1, 1, 2, 36, 2, 2, 36, 2, 1, 1, 2, 1, 2, 36, 2, 36, 36, 1, 2, 1, 36, 36, 36, 36, 36, 1, 2, 2, 36, 1, 1, 1, 36, 1, 2, 36, 2, 36, 1, 1, 2, 36, 36, 1, 1, 36, 36, 36, 1, 1, 36, 2, 2, 36, 36, 2, 36, 2, 36, 2, 36, 36],
      "exportMode": 0,
      "arrayMode": 0
    }
  ]
}